md_changelog/__init__.py
md_changelog/entry.py
md_changelog/exceptions.py
md_changelog/main.py
md_changelog/tokens.py
md_changelog-0.1.4.dist-info/DESCRIPTION.rst
md_changelog-0.1.4.dist-info/METADATA
md_changelog-0.1.4.dist-info/RECORD
md_changelog-0.1.4.dist-info/WHEEL
md_changelog-0.1.4.dist-info/entry_points.txt
md_changelog-0.1.4.dist-info/metadata.json
md_changelog-0.1.4.dist-info/top_level.txt
