Metadata-Version: 2.0
Name: md-changelog
Version: 0.1.4
Summary: Changelog command-line tool manager
Home-page: UNKNOWN
Author: Maksim Ekimovskii
Author-email: ekimovsky.maksim@gmail.com
License: MIT
Platform: UNKNOWN
